{"expireTime":9007200957394896000,"key":"transformer-remark-markdown-ast-3e44243488a9b46c24ed94af21b7ea57-gatsby-remark-external-linksgatsby-remark-imagesgatsby-remark-code-titlesgatsby-remark-prismjs-","val":{"type":"root","children":[{"type":"list","ordered":false,"start":null,"spread":false,"children":[{"type":"listItem","spread":false,"checked":null,"children":[{"type":"paragraph","children":[{"type":"text","value":"Microsoft - Engineering Virtual Experience ","position":{"start":{"line":2,"column":3,"offset":3},"end":{"line":2,"column":46,"offset":46},"indent":[]}},{"type":"link","title":null,"url":"https://insidesherpa.s3.amazonaws.com/completion-certificates/Microsoft/ms2CK9b2SCWGXwPMS_Microsoft_nXPiDeZbPmvKvvjHA_completion_certificate.pdf","children":[{"type":"text","value":"CERTIFICATE","position":{"start":{"line":2,"column":47,"offset":47},"end":{"line":2,"column":58,"offset":58},"indent":[]}}],"position":{"start":{"line":2,"column":46,"offset":46},"end":{"line":2,"column":205,"offset":205},"indent":[]},"data":{"hProperties":{"target":"_blank","rel":"nofollow noopener noreferrer"}}}],"position":{"start":{"line":2,"column":3,"offset":3},"end":{"line":2,"column":205,"offset":205},"indent":[]}}],"position":{"start":{"line":2,"column":1,"offset":1},"end":{"line":2,"column":205,"offset":205},"indent":[]}},{"type":"listItem","spread":false,"checked":null,"children":[{"type":"paragraph","children":[{"type":"text","value":"Deloitte - Technology Consulting Virtual Internship ","position":{"start":{"line":3,"column":3,"offset":208},"end":{"line":3,"column":55,"offset":260},"indent":[]}},{"type":"link","title":null,"url":"https://insidesherpa.s3.amazonaws.com/completion-certificates/Deloitte/FqFtWwQzNxJ8Qsh5H_Deloitte_nXPiDeZbPmvKvvjHA_completion_certificate.pdf","children":[{"type":"text","value":"CERTIFICATE","position":{"start":{"line":3,"column":56,"offset":261},"end":{"line":3,"column":67,"offset":272},"indent":[]}}],"position":{"start":{"line":3,"column":55,"offset":260},"end":{"line":3,"column":212,"offset":417},"indent":[]},"data":{"hProperties":{"target":"_blank","rel":"nofollow noopener noreferrer"}}}],"position":{"start":{"line":3,"column":3,"offset":208},"end":{"line":3,"column":212,"offset":417},"indent":[]}}],"position":{"start":{"line":3,"column":1,"offset":206},"end":{"line":3,"column":212,"offset":417},"indent":[]}},{"type":"listItem","spread":false,"checked":null,"children":[{"type":"paragraph","children":[{"type":"text","value":"JPMorgan Chase & Co. Software Engineering Virtual Experience ","position":{"start":{"line":4,"column":3,"offset":420},"end":{"line":4,"column":64,"offset":481},"indent":[]}},{"type":"link","title":null,"url":"https://insidesherpa.s3.amazonaws.com/completion-certificates/JP%20Morgan/R5iK7HMxJGBgaSbvk_JPMorgan%20Chase_nXPiDeZbPmvKvvjHA_completion_certificate.pdf","children":[{"type":"text","value":"CERTIFICATE","position":{"start":{"line":4,"column":65,"offset":482},"end":{"line":4,"column":76,"offset":493},"indent":[]}}],"position":{"start":{"line":4,"column":64,"offset":481},"end":{"line":4,"column":232,"offset":649},"indent":[]},"data":{"hProperties":{"target":"_blank","rel":"nofollow noopener noreferrer"}}}],"position":{"start":{"line":4,"column":3,"offset":420},"end":{"line":4,"column":232,"offset":649},"indent":[]}}],"position":{"start":{"line":4,"column":1,"offset":418},"end":{"line":4,"column":232,"offset":649},"indent":[]}},{"type":"listItem","spread":false,"checked":null,"children":[{"type":"paragraph","children":[{"type":"text","value":"KPMG - Data Analytics Consulting Virtual Internship ","position":{"start":{"line":5,"column":3,"offset":652},"end":{"line":5,"column":55,"offset":704},"indent":[]}},{"type":"link","title":null,"url":"https://insidesherpa.s3.amazonaws.com/completion-certificates/KPMG/m7W4GMqeT3bh9Nb2c_KPMG_nXPiDeZbPmvKvvjHA_completion_certificate.pdf","children":[{"type":"text","value":"CERTIFICATE","position":{"start":{"line":5,"column":56,"offset":705},"end":{"line":5,"column":67,"offset":716},"indent":[]}}],"position":{"start":{"line":5,"column":55,"offset":704},"end":{"line":5,"column":204,"offset":853},"indent":[]},"data":{"hProperties":{"target":"_blank","rel":"nofollow noopener noreferrer"}}}],"position":{"start":{"line":5,"column":3,"offset":652},"end":{"line":5,"column":204,"offset":853},"indent":[]}}],"position":{"start":{"line":5,"column":1,"offset":650},"end":{"line":5,"column":204,"offset":853},"indent":[]}},{"type":"listItem","spread":false,"checked":null,"children":[{"type":"paragraph","children":[{"type":"text","value":"Y Combinator Virtual Experience ","position":{"start":{"line":6,"column":3,"offset":856},"end":{"line":6,"column":35,"offset":888},"indent":[]}},{"type":"link","title":null,"url":"https://drive.google.com/file/d/1btrRl7BWopLhOWudEI1RTOSl7qsCl-yS/view","children":[{"type":"text","value":"CERTIFICATE","position":{"start":{"line":6,"column":36,"offset":889},"end":{"line":6,"column":47,"offset":900},"indent":[]}}],"position":{"start":{"line":6,"column":35,"offset":888},"end":{"line":6,"column":120,"offset":973},"indent":[]},"data":{"hProperties":{"target":"_blank","rel":"nofollow noopener noreferrer"}}}],"position":{"start":{"line":6,"column":3,"offset":856},"end":{"line":6,"column":120,"offset":973},"indent":[]}}],"position":{"start":{"line":6,"column":1,"offset":854},"end":{"line":6,"column":120,"offset":973},"indent":[]}}],"position":{"start":{"line":2,"column":1,"offset":1},"end":{"line":6,"column":120,"offset":973},"indent":[1,1,1,1]}}],"position":{"start":{"line":1,"column":1,"offset":0},"end":{"line":7,"column":1,"offset":974}}}}